Metadata-Version: 1.1
Name: PleaseWork
Version: 0.0.4
Summary: I dont`t now
Home-page: UNKNOWN
Author: Thiago Comelli
Author-email: thiago.comelli@outlook.com
License: MIT
Keywords: Random
Platform: UNKNOWN
Classifier: Development Status :: 5 - Production/Stable
Classifier: Intended Audience :: Education
Classifier: Operating System :: POSIX
Classifier: License :: OSI Approved :: MIT License
Classifier: Programming Language :: Python :: 3
